src/segment_scan8.v
`timescale 1ns/1ps
// Logical outputs are active-high. Apply board polarity in the wrapper.
// Each slot contains one active interval followed by one blank interval.
module segment_scan8 (
    input wire clk, rst, enable,
    input wire [31:0] digits,
    output reg [7:0] select,
    output reg [7:0] segments,
    output reg [2:0] index
);
    reg blank;
    reg [3:0] nibble;
    always @(posedge clk) begin
        if (rst) begin
            index <= 0;
            blank <= 1'b1;
        end else if (enable) begin
            blank <= ~blank;
            if (!blank) index <= index + 1'b1;
        end
    end
    always @* begin
        nibble = digits >> (index * 4);
        select = blank ? 8'h00 : (8'h01 << index);
        // abcdefg, dp: decimal point remains off.
        case (nibble)
            4'h0: segments = 8'b11111100;
            4'h1: segments = 8'b01100000;
            4'h2: segments = 8'b11011010;
            4'h3: segments = 8'b11110010;
            4'h4: segments = 8'b01100110;
            4'h5: segments = 8'b10110110;
            4'h6: segments = 8'b10111110;
            4'h7: segments = 8'b11100000;
            4'h8: segments = 8'b11111110;
            4'h9: segments = 8'b11110110;
            4'ha: segments = 8'b11101110;
            4'hb: segments = 8'b00111110;
            4'hc: segments = 8'b10011100;
            4'hd: segments = 8'b01111010;
            4'he: segments = 8'b10011110;
            4'hf: segments = 8'b10001110;
            default: segments = 8'h00;
        endcase
    end
endmodule

sim/tb_segment_scan8.sv
`timescale 1ns/1ps
module tb_segment_scan8;
reg clk=0, rst=1;
integer checks=0;
always #5 clk=~clk;
task step; begin @(posedge clk); #1; end endtask
task check(input condition, input [8*100-1:0] description);
begin
    checks=checks+1;
    if (condition !== 1'b1) begin
        $display("LAB2_FAIL %0s time=%0t",description,$time);
        $fatal(1,"check failed");
    end
end
endtask
task finish;
begin
    $display("LAB2_PASS segment_scan8 checks=%0d",checks);
    $finish;
end
endtask
initial begin $dumpfile("wave.vcd"); $dumpvars(0,tb_segment_scan8); end
initial begin #100000; $fatal(1,"watchdog timeout"); end
reg enable=0;
reg [31:0] digits=32'h76543210;
wire [7:0] select, segments;
wire [2:0] index;
segment_scan8 dut(clk,rst,enable,digits,select,segments,index);
reg [7:0] expected[0:15];
integer bank, position, lap;
initial begin
    // Truth-table values, ordered 0..F with abcdefg and dp.
    expected[0]=8'hfc; expected[1]=8'h60; expected[2]=8'hda; expected[3]=8'hf2;
    expected[4]=8'h66; expected[5]=8'hb6; expected[6]=8'hbe; expected[7]=8'he0;
    expected[8]=8'hfe; expected[9]=8'hf6; expected[10]=8'hee; expected[11]=8'h3e;
    expected[12]=8'h9c; expected[13]=8'h7a; expected[14]=8'h9e; expected[15]=8'h8e;
    step; check(select===0 && index===0,"reset blanks digit zero"); rst=0;
    for(bank=0;bank<2;bank=bank+1) begin
        digits=bank ? 32'hfedcba98 : 32'h76543210;
        for(lap=0;lap<2;lap=lap+1) begin
            for(position=0;position<8;position=position+1) begin
                enable=1; step;
                check(index===position,"position order");
                check(select===(1<<position),"exactly intended digit active");
                check(segments===expected[bank*8+position],"hex truth table");
                enable=0; step;
                check(select===(1<<position),"enable zero holds active slot");
                enable=1; step;
                check(select===0,"blank interval between every digit");
                enable=0; step; check(select===0,"blank interval hold");
            end
        end
    end
    enable=1; step; rst=1; step;
    check(select===0 && index===0,"reset from active scan"); finish;
end
endmodule

vivado/lab2_segment_scan.sim/sim_1/behav/xsim/wave.vcd
$date
   Mon Sep 21 14:42:23 2026
$end

$version
  2026.1
  $dumpfile ("wave.vcd") 
$end

$timescale
  1ps
$end

$scope module tb_segment_scan8 $end
$var reg 1 ! clk $end
$var reg 1 " rst $end
$var integer 32 # checks [31:0] $end
$var reg 1 $ enable $end
$var reg 32 % digits [31:0] $end
$var wire 8 & select [7:0] $end
$var wire 8 ' segments [7:0] $end
$var wire 3 ( index [2:0] $end
$var integer 32 ) bank [31:0] $end
$var integer 32 * position [31:0] $end
$var integer 32 + lap [31:0] $end
$scope module dut $end
$var wire 1 , clk $end
$var wire 1 - rst $end
$var wire 1 . enable $end
$var wire 32 / digits [31:0] $end
$var reg 8 0 select [7:0] $end
$var reg 8 1 segments [7:0] $end
$var reg 3 2 index [2:0] $end
$var reg 1 3 blank $end
$var reg 4 4 nibble [3:0] $end
$upscope $end
$scope task step $end
$upscope $end
$scope task check $end
$var reg 1 5 condition $end
$var reg 800 6 description [799:0] $end
$upscope $end
$scope task finish $end
$upscope $end
$upscope $end
$enddefinitions $end

#0
$dumpvars
0!
1"
b0 #
0$
b1110110010101000011001000010000 %
bx &
b0 '
bx (
bx )
bx *
bx +
0,
1-
0.
b1110110010101000011001000010000 /
bx 0
b0 1
bx 2
x3
bx 4
x5
bx 6
$end

#5000
1!
b0 &
b11111100 '
b0 (
1,
b0 0
b11111100 1
b0 2
13
b0 4

#6000
0"
b1 #
1$
b0 )
b0 *
b0 +
0-
1.
15
b111001001100101011100110110010101110100001000000110001001101100011000010110111001101011011100110010000001100100011010010110011101101001011101000010000001111010011001010111001001101111 6

#10000
0!
0,

#15000
1!
b1 &
1,
b1 0
03

#16000
b100 #
0$
0.
b11010000110010101111000001000000111010001110010011101010111010001101000001000000111010001100001011000100110110001100101 6

#20000
0!
0,

#25000
1!
1,

#26000
b101 #
1$
1.
b110010101101110011000010110001001101100011001010010000001111010011001010111001001101111001000000110100001101111011011000110010001110011001000000110000101100011011101000110100101110110011001010010000001110011011011000110111101110100 6

#30000
0!
0,

#35000
1!
b0 &
b1100000 '
b1 (
1,
b0 0
b1100000 1
b1 2
13
b1 4

#36000
b110 #
0$
0.
b1100010011011000110000101101110011010110010000001101001011011100111010001100101011100100111011001100001011011000010000001100010011001010111010001110111011001010110010101101110001000000110010101110110011001010111001001111001001000000110010001101001011001110110100101110100 6

#40000
0!
0,

#45000
1!
1,

#46000
b111 #
1$
b1 *
1.
b1100010011011000110000101101110011010110010000001101001011011100111010001100101011100100111011001100001011011000010000001101000011011110110110001100100 6

#50000
0!
0,

#55000
1!
b10 &
1,
b10 0
03

#56000
b1010 #
0$
0.
b11010000110010101111000001000000111010001110010011101010111010001101000001000000111010001100001011000100110110001100101 6

#60000
0!
0,

#65000
1!
1,

#66000
b1011 #
1$
1.
b110010101101110011000010110001001101100011001010010000001111010011001010111001001101111001000000110100001101111011011000110010001110011001000000110000101100011011101000110100101110110011001010010000001110011011011000110111101110100 6

#70000
0!
0,

#75000
1!
b0 &
b11011010 '
b10 (
1,
b0 0
b11011010 1
b10 2
13
b10 4

#76000
b1100 #
0$
0.
b1100010011011000110000101101110011010110010000001101001011011100111010001100101011100100111011001100001011011000010000001100010011001010111010001110111011001010110010101101110001000000110010101110110011001010111001001111001001000000110010001101001011001110110100101110100 6

#80000
0!
0,

#85000
1!
1,

#86000
b1101 #
1$
b10 *
1.
b1100010011011000110000101101110011010110010000001101001011011100111010001100101011100100111011001100001011011000010000001101000011011110110110001100100 6

#90000
0!
0,

#95000
1!
b100 &
1,
b100 0
03

#96000
b10000 #
0$
0.
b11010000110010101111000001000000111010001110010011101010111010001101000001000000111010001100001011000100110110001100101 6

#100000
0!
0,

#105000
1!
1,

#106000
b10001 #
1$
1.
b110010101101110011000010110001001101100011001010010000001111010011001010111001001101111001000000110100001101111011011000110010001110011001000000110000101100011011101000110100101110110011001010010000001110011011011000110111101110100 6

#110000
0!
0,

#115000
1!
b0 &
b11110010 '
b11 (
1,
b0 0
b11110010 1
b11 2
13
b11 4

#116000
b10010 #
0$
0.
b1100010011011000110000101101110011010110010000001101001011011100111010001100101011100100111011001100001011011000010000001100010011001010111010001110111011001010110010101101110001000000110010101110110011001010111001001111001001000000110010001101001011001110110100101110100 6

#120000
0!
0,

#125000
1!
1,

#126000
b10011 #
1$
b11 *
1.
b1100010011011000110000101101110011010110010000001101001011011100111010001100101011100100111011001100001011011000010000001101000011011110110110001100100 6

#130000
0!
0,

#135000
1!
b1000 &
1,
b1000 0
03

#136000
b10110 #
0$
0.
b11010000110010101111000001000000111010001110010011101010111010001101000001000000111010001100001011000100110110001100101 6

#140000
0!
0,

#145000
1!
1,

#146000
b10111 #
1$
1.
b110010101101110011000010110001001101100011001010010000001111010011001010111001001101111001000000110100001101111011011000110010001110011001000000110000101100011011101000110100101110110011001010010000001110011011011000110111101110100 6

#150000
0!
0,

#155000
1!
b0 &
b1100110 '
b100 (
1,
b0 0
b1100110 1
b100 2
13
b100 4

#156000
b11000 #
0$
0.
b1100010011011000110000101101110011010110010000001101001011011100111010001100101011100100111011001100001011011000010000001100010011001010111010001110111011001010110010101101110001000000110010101110110011001010111001001111001001000000110010001101001011001110110100101110100 6

#160000
0!
0,

#165000
1!
1,

#166000
b11001 #
1$
b100 *
1.
b1100010011011000110000101101110011010110010000001101001011011100111010001100101011100100111011001100001011011000010000001101000011011110110110001100100 6

#170000
0!
0,

#175000
1!
b10000 &
1,
b10000 0
03

#176000
b11100 #
0$
0.
b11010000110010101111000001000000111010001110010011101010111010001101000001000000111010001100001011000100110110001100101 6

#180000
0!
0,

#185000
1!
1,

#186000
b11101 #
1$
1.
b110010101101110011000010110001001101100011001010010000001111010011001010111001001101111001000000110100001101111011011000110010001110011001000000110000101100011011101000110100101110110011001010010000001110011011011000110111101110100 6

#190000
0!
0,

#195000
1!
b0 &
b10110110 '
b101 (
1,
b0 0
b10110110 1
b101 2
13
b101 4

#196000
b11110 #
0$
0.
b1100010011011000110000101101110011010110010000001101001011011100111010001100101011100100111011001100001011011000010000001100010011001010111010001110111011001010110010101101110001000000110010101110110011001010111001001111001001000000110010001101001011001110110100101110100 6

#200000
0!
0,

#205000
1!
1,

#206000
b11111 #
1$
b101 *
1.
b1100010011011000110000101101110011010110010000001101001011011100111010001100101011100100111011001100001011011000010000001101000011011110110110001100100 6

#210000
0!
0,

#215000
1!
b100000 &
1,
b100000 0
03

#216000
b100010 #
0$
0.
b11010000110010101111000001000000111010001110010011101010111010001101000001000000111010001100001011000100110110001100101 6

#220000
0!
0,

#225000
1!
1,

#226000
b100011 #
1$
1.
b110010101101110011000010110001001101100011001010010000001111010011001010111001001101111001000000110100001101111011011000110010001110011001000000110000101100011011101000110100101110110011001010010000001110011011011000110111101110100 6

#230000
0!
0,

#235000
1!
b0 &
b10111110 '
b110 (
1,
b0 0
b10111110 1
b110 2
13
b110 4

#236000
b100100 #
0$
0.
b1100010011011000110000101101110011010110010000001101001011011100111010001100101011100100111011001100001011011000010000001100010011001010111010001110111011001010110010101101110001000000110010101110110011001010111001001111001001000000110010001101001011001110110100101110100 6

#240000
0!
0,

#245000
1!
1,

#246000
b100101 #
1$
b110 *
1.
b1100010011011000110000101101110011010110010000001101001011011100111010001100101011100100111011001100001011011000010000001101000011011110110110001100100 6

#250000
0!
0,

#255000
1!
b1000000 &
1,
b1000000 0
03

#256000
b101000 #
0$
0.
b11010000110010101111000001000000111010001110010011101010111010001101000001000000111010001100001011000100110110001100101 6

#260000
0!
0,

#265000
1!
1,

#266000
b101001 #
1$
1.
b110010101101110011000010110001001101100011001010010000001111010011001010111001001101111001000000110100001101111011011000110010001110011001000000110000101100011011101000110100101110110011001010010000001110011011011000110111101110100 6

#270000
0!
0,

#275000
1!
b0 &
b11100000 '
b111 (
1,
b0 0
b11100000 1
b111 2
13
b111 4

#276000
b101010 #
0$
0.
b1100010011011000110000101101110011010110010000001101001011011100111010001100101011100100111011001100001011011000010000001100010011001010111010001110111011001010110010101101110001000000110010101110110011001010111001001111001001000000110010001101001011001110110100101110100 6

#280000
0!
0,

#285000
1!
1,

#286000
b101011 #
1$
b111 *
1.
b1100010011011000110000101101110011010110010000001101001011011100111010001100101011100100111011001100001011011000010000001101000011011110110110001100100 6

#290000
0!
0,

#295000
1!
b10000000 &
1,
b10000000 0
03

#296000
b101110 #
0$
0.
b11010000110010101111000001000000111010001110010011101010111010001101000001000000111010001100001011000100110110001100101 6

#300000
0!
0,

#305000
1!
1,

#306000
b101111 #
1$
1.
b110010101101110011000010110001001101100011001010010000001111010011001010111001001101111001000000110100001101111011011000110010001110011001000000110000101100011011101000110100101110110011001010010000001110011011011000110111101110100 6

#310000
0!
0,

#315000
1!
b0 &
b11111100 '
b0 (
1,
b0 0
b11111100 1
b0 2
13
b0 4

#316000
b110000 #
0$
0.
b1100010011011000110000101101110011010110010000001101001011011100111010001100101011100100111011001100001011011000010000001100010011001010111010001110111011001010110010101101110001000000110010101110110011001010111001001111001001000000110010001101001011001110110100101110100 6

#320000
0!
0,

#325000
1!
1,

#326000
b110001 #
1$
b0 *
b1 +
1.
b1100010011011000110000101101110011010110010000001101001011011100111010001100101011100100111011001100001011011000010000001101000011011110110110001100100 6

#330000
0!
0,

#335000
1!
b1 &
1,
b1 0
03

#336000
b110100 #
0$
0.
b11010000110010101111000001000000111010001110010011101010111010001101000001000000111010001100001011000100110110001100101 6

#340000
0!
0,

#345000
1!
1,

#346000
b110101 #
1$
1.
b110010101101110011000010110001001101100011001010010000001111010011001010111001001101111001000000110100001101111011011000110010001110011001000000110000101100011011101000110100101110110011001010010000001110011011011000110111101110100 6

#350000
0!
0,

#355000
1!
b0 &
b1100000 '
b1 (
1,
b0 0
b1100000 1
b1 2
13
b1 4

#356000
b110110 #
0$
0.
b1100010011011000110000101101110011010110010000001101001011011100111010001100101011100100111011001100001011011000010000001100010011001010111010001110111011001010110010101101110001000000110010101110110011001010111001001111001001000000110010001101001011001110110100101110100 6

#360000
0!
0,

#365000
1!
1,

#366000
b110111 #
1$
b1 *
1.
b1100010011011000110000101101110011010110010000001101001011011100111010001100101011100100111011001100001011011000010000001101000011011110110110001100100 6

#370000
0!
0,

#375000
1!
b10 &
1,
b10 0
03

#376000
b111010 #
0$
0.
b11010000110010101111000001000000111010001110010011101010111010001101000001000000111010001100001011000100110110001100101 6

#380000
0!
0,

#385000
1!
1,

#386000
b111011 #
1$
1.
b110010101101110011000010110001001101100011001010010000001111010011001010111001001101111001000000110100001101111011011000110010001110011001000000110000101100011011101000110100101110110011001010010000001110011011011000110111101110100 6

#390000
0!
0,

#395000
1!
b0 &
b11011010 '
b10 (
1,
b0 0
b11011010 1
b10 2
13
b10 4

#396000
b111100 #
0$
0.
b1100010011011000110000101101110011010110010000001101001011011100111010001100101011100100111011001100001011011000010000001100010011001010111010001110111011001010110010101101110001000000110010101110110011001010111001001111001001000000110010001101001011001110110100101110100 6

#400000
0!
0,

#405000
1!
1,

#406000
b111101 #
1$
b10 *
1.
b1100010011011000110000101101110011010110010000001101001011011100111010001100101011100100111011001100001011011000010000001101000011011110110110001100100 6

#410000
0!
0,

#415000
1!
b100 &
1,
b100 0
03

#416000
b1000000 #
0$
0.
b11010000110010101111000001000000111010001110010011101010111010001101000001000000111010001100001011000100110110001100101 6

#420000
0!
0,

#425000
1!
1,

#426000
b1000001 #
1$
1.
b110010101101110011000010110001001101100011001010010000001111010011001010111001001101111001000000110100001101111011011000110010001110011001000000110000101100011011101000110100101110110011001010010000001110011011011000110111101110100 6

#430000
0!
0,

#435000
1!
b0 &
b11110010 '
b11 (
1,
b0 0
b11110010 1
b11 2
13
b11 4

#436000
b1000010 #
0$
0.
b1100010011011000110000101101110011010110010000001101001011011100111010001100101011100100111011001100001011011000010000001100010011001010111010001110111011001010110010101101110001000000110010101110110011001010111001001111001001000000110010001101001011001110110100101110100 6

#440000
0!
0,

#445000
1!
1,

#446000
b1000011 #
1$
b11 *
1.
b1100010011011000110000101101110011010110010000001101001011011100111010001100101011100100111011001100001011011000010000001101000011011110110110001100100 6

#450000
0!
0,

#455000
1!
b1000 &
1,
b1000 0
03

#456000
b1000110 #
0$
0.
b11010000110010101111000001000000111010001110010011101010111010001101000001000000111010001100001011000100110110001100101 6

#460000
0!
0,

#465000
1!
1,

#466000
b1000111 #
1$
1.
b110010101101110011000010110001001101100011001010010000001111010011001010111001001101111001000000110100001101111011011000110010001110011001000000110000101100011011101000110100101110110011001010010000001110011011011000110111101110100 6

#470000
0!
0,

#475000
1!
b0 &
b1100110 '
b100 (
1,
b0 0
b1100110 1
b100 2
13
b100 4

#476000
b1001000 #
0$
0.
b1100010011011000110000101101110011010110010000001101001011011100111010001100101011100100111011001100001011011000010000001100010011001010111010001110111011001010110010101101110001000000110010101110110011001010111001001111001001000000110010001101001011001110110100101110100 6

#480000
0!
0,

#485000
1!
1,

#486000
b1001001 #
1$
b100 *
1.
b1100010011011000110000101101110011010110010000001101001011011100111010001100101011100100111011001100001011011000010000001101000011011110110110001100100 6

#490000
0!
0,

#495000
1!
b10000 &
1,
b10000 0
03

#496000
b1001100 #
0$
0.
b11010000110010101111000001000000111010001110010011101010111010001101000001000000111010001100001011000100110110001100101 6

#500000
0!
0,

#505000
1!
1,

#506000
b1001101 #
1$
1.
b110010101101110011000010110001001101100011001010010000001111010011001010111001001101111001000000110100001101111011011000110010001110011001000000110000101100011011101000110100101110110011001010010000001110011011011000110111101110100 6

#510000
0!
0,

#515000
1!
b0 &
b10110110 '
b101 (
1,
b0 0
b10110110 1
b101 2
13
b101 4

#516000
b1001110 #
0$
0.
b1100010011011000110000101101110011010110010000001101001011011100111010001100101011100100111011001100001011011000010000001100010011001010111010001110111011001010110010101101110001000000110010101110110011001010111001001111001001000000110010001101001011001110110100101110100 6

#520000
0!
0,

#525000
1!
1,

#526000
b1001111 #
1$
b101 *
1.
b1100010011011000110000101101110011010110010000001101001011011100111010001100101011100100111011001100001011011000010000001101000011011110110110001100100 6

#530000
0!
0,

#535000
1!
b100000 &
1,
b100000 0
03

#536000
b1010010 #
0$
0.
b11010000110010101111000001000000111010001110010011101010111010001101000001000000111010001100001011000100110110001100101 6

#540000
0!
0,

#545000
1!
1,

#546000
b1010011 #
1$
1.
b110010101101110011000010110001001101100011001010010000001111010011001010111001001101111001000000110100001101111011011000110010001110011001000000110000101100011011101000110100101110110011001010010000001110011011011000110111101110100 6

#550000
0!
0,

#555000
1!
b0 &
b10111110 '
b110 (
1,
b0 0
b10111110 1
b110 2
13
b110 4

#556000
b1010100 #
0$
0.
b1100010011011000110000101101110011010110010000001101001011011100111010001100101011100100111011001100001011011000010000001100010011001010111010001110111011001010110010101101110001000000110010101110110011001010111001001111001001000000110010001101001011001110110100101110100 6

#560000
0!
0,

#565000
1!
1,

#566000
b1010101 #
1$
b110 *
1.
b1100010011011000110000101101110011010110010000001101001011011100111010001100101011100100111011001100001011011000010000001101000011011110110110001100100 6

#570000
0!
0,

#575000
1!
b1000000 &
1,
b1000000 0
03

#576000
b1011000 #
0$
0.
b11010000110010101111000001000000111010001110010011101010111010001101000001000000111010001100001011000100110110001100101 6

#580000
0!
0,

#585000
1!
1,

#586000
b1011001 #
1$
1.
b110010101101110011000010110001001101100011001010010000001111010011001010111001001101111001000000110100001101111011011000110010001110011001000000110000101100011011101000110100101110110011001010010000001110011011011000110111101110100 6

#590000
0!
0,

#595000
1!
b0 &
b11100000 '
b111 (
1,
b0 0
b11100000 1
b111 2
13
b111 4

#596000
b1011010 #
0$
0.
b1100010011011000110000101101110011010110010000001101001011011100111010001100101011100100111011001100001011011000010000001100010011001010111010001110111011001010110010101101110001000000110010101110110011001010111001001111001001000000110010001101001011001110110100101110100 6

#600000
0!
0,

#605000
1!
1,

#606000
b1011011 #
1$
b111 *
1.
b1100010011011000110000101101110011010110010000001101001011011100111010001100101011100100111011001100001011011000010000001101000011011110110110001100100 6

#610000
0!
0,

#615000
1!
b10000000 &
1,
b10000000 0
03

#616000
b1011110 #
0$
0.
b11010000110010101111000001000000111010001110010011101010111010001101000001000000111010001100001011000100110110001100101 6

#620000
0!
0,

#625000
1!
1,

#626000
b1011111 #
1$
1.
b110010101101110011000010110001001101100011001010010000001111010011001010111001001101111001000000110100001101111011011000110010001110011001000000110000101100011011101000110100101110110011001010010000001110011011011000110111101110100 6

#630000
0!
0,

#635000
1!
b0 &
b11111100 '
b0 (
1,
b0 0
b11111100 1
b0 2
13
b0 4

#636000
b1100000 #
0$
0.
b1100010011011000110000101101110011010110010000001101001011011100111010001100101011100100111011001100001011011000010000001100010011001010111010001110111011001010110010101101110001000000110010101110110011001010111001001111001001000000110010001101001011001110110100101110100 6

#640000
0!
0,

#645000
1!
1,

#646000
b1100001 #
1$
b11111110110111001011101010011000 %
b11111110 '
b1 )
b0 *
b0 +
1.
b11111110110111001011101010011000 /
b11111110 1
b1000 4
b1100010011011000110000101101110011010110010000001101001011011100111010001100101011100100111011001100001011011000010000001101000011011110110110001100100 6

#650000
0!
0,

#655000
1!
b1 &
1,
b1 0
03

#656000
b1100100 #
0$
0.
b11010000110010101111000001000000111010001110010011101010111010001101000001000000111010001100001011000100110110001100101 6

#660000
0!
0,

#665000
1!
1,

#666000
b1100101 #
1$
1.
b110010101101110011000010110001001101100011001010010000001111010011001010111001001101111001000000110100001101111011011000110010001110011001000000110000101100011011101000110100101110110011001010010000001110011011011000110111101110100 6

#670000
0!
0,

#675000
1!
b0 &
b11110110 '
b1 (
1,
b0 0
b11110110 1
b1 2
13
b1001 4

#676000
b1100110 #
0$
0.
b1100010011011000110000101101110011010110010000001101001011011100111010001100101011100100111011001100001011011000010000001100010011001010111010001110111011001010110010101101110001000000110010101110110011001010111001001111001001000000110010001101001011001110110100101110100 6

#680000
0!
0,

#685000
1!
1,

#686000
b1100111 #
1$
b1 *
1.
b1100010011011000110000101101110011010110010000001101001011011100111010001100101011100100111011001100001011011000010000001101000011011110110110001100100 6

#690000
0!
0,

#695000
1!
b10 &
1,
b10 0
03

#696000
b1101010 #
0$
0.
b11010000110010101111000001000000111010001110010011101010111010001101000001000000111010001100001011000100110110001100101 6

#700000
0!
0,

#705000
1!
1,

#706000
b1101011 #
1$
1.
b110010101101110011000010110001001101100011001010010000001111010011001010111001001101111001000000110100001101111011011000110010001110011001000000110000101100011011101000110100101110110011001010010000001110011011011000110111101110100 6

#710000
0!
0,

#715000
1!
b0 &
b11101110 '
b10 (
1,
b0 0
b11101110 1
b10 2
13
b1010 4

#716000
b1101100 #
0$
0.
b1100010011011000110000101101110011010110010000001101001011011100111010001100101011100100111011001100001011011000010000001100010011001010111010001110111011001010110010101101110001000000110010101110110011001010111001001111001001000000110010001101001011001110110100101110100 6

#720000
0!
0,

#725000
1!
1,

#726000
b1101101 #
1$
b10 *
1.
b1100010011011000110000101101110011010110010000001101001011011100111010001100101011100100111011001100001011011000010000001101000011011110110110001100100 6

#730000
0!
0,

#735000
1!
b100 &
1,
b100 0
03

#736000
b1110000 #
0$
0.
b11010000110010101111000001000000111010001110010011101010111010001101000001000000111010001100001011000100110110001100101 6

#740000
0!
0,

#745000
1!
1,

#746000
b1110001 #
1$
1.
b110010101101110011000010110001001101100011001010010000001111010011001010111001001101111001000000110100001101111011011000110010001110011001000000110000101100011011101000110100101110110011001010010000001110011011011000110111101110100 6

#750000
0!
0,

#755000
1!
b0 &
b111110 '
b11 (
1,
b0 0
b111110 1
b11 2
13
b1011 4

#756000
b1110010 #
0$
0.
b1100010011011000110000101101110011010110010000001101001011011100111010001100101011100100111011001100001011011000010000001100010011001010111010001110111011001010110010101101110001000000110010101110110011001010111001001111001001000000110010001101001011001110110100101110100 6

#760000
0!
0,

#765000
1!
1,

#766000
b1110011 #
1$
b11 *
1.
b1100010011011000110000101101110011010110010000001101001011011100111010001100101011100100111011001100001011011000010000001101000011011110110110001100100 6

#770000
0!
0,

#775000
1!
b1000 &
1,
b1000 0
03

#776000
b1110110 #
0$
0.
b11010000110010101111000001000000111010001110010011101010111010001101000001000000111010001100001011000100110110001100101 6

#780000
0!
0,

#785000
1!
1,

#786000
b1110111 #
1$
1.
b110010101101110011000010110001001101100011001010010000001111010011001010111001001101111001000000110100001101111011011000110010001110011001000000110000101100011011101000110100101110110011001010010000001110011011011000110111101110100 6

#790000
0!
0,

#795000
1!
b0 &
b10011100 '
b100 (
1,
b0 0
b10011100 1
b100 2
13
b1100 4

#796000
b1111000 #
0$
0.
b1100010011011000110000101101110011010110010000001101001011011100111010001100101011100100111011001100001011011000010000001100010011001010111010001110111011001010110010101101110001000000110010101110110011001010111001001111001001000000110010001101001011001110110100101110100 6

#800000
0!
0,

#805000
1!
1,

#806000
b1111001 #
1$
b100 *
1.
b1100010011011000110000101101110011010110010000001101001011011100111010001100101011100100111011001100001011011000010000001101000011011110110110001100100 6

#810000
0!
0,

#815000
1!
b10000 &
1,
b10000 0
03

#816000
b1111100 #
0$
0.
b11010000110010101111000001000000111010001110010011101010111010001101000001000000111010001100001011000100110110001100101 6

#820000
0!
0,

#825000
1!
1,

#826000
b1111101 #
1$
1.
b110010101101110011000010110001001101100011001010010000001111010011001010111001001101111001000000110100001101111011011000110010001110011001000000110000101100011011101000110100101110110011001010010000001110011011011000110111101110100 6

#830000
0!
0,

#835000
1!
b0 &
b1111010 '
b101 (
1,
b0 0
b1111010 1
b101 2
13
b1101 4

#836000
b1111110 #
0$
0.
b1100010011011000110000101101110011010110010000001101001011011100111010001100101011100100111011001100001011011000010000001100010011001010111010001110111011001010110010101101110001000000110010101110110011001010111001001111001001000000110010001101001011001110110100101110100 6

#840000
0!
0,

#845000
1!
1,

#846000
b1111111 #
1$
b101 *
1.
b1100010011011000110000101101110011010110010000001101001011011100111010001100101011100100111011001100001011011000010000001101000011011110110110001100100 6

#850000
0!
0,

#855000
1!
b100000 &
1,
b100000 0
03

#856000
b10000010 #
0$
0.
b11010000110010101111000001000000111010001110010011101010111010001101000001000000111010001100001011000100110110001100101 6

#860000
0!
0,

#865000
1!
1,

#866000
b10000011 #
1$
1.
b110010101101110011000010110001001101100011001010010000001111010011001010111001001101111001000000110100001101111011011000110010001110011001000000110000101100011011101000110100101110110011001010010000001110011011011000110111101110100 6

#870000
0!
0,

#875000
1!
b0 &
b10011110 '
b110 (
1,
b0 0
b10011110 1
b110 2
13
b1110 4

#876000
b10000100 #
0$
0.
b1100010011011000110000101101110011010110010000001101001011011100111010001100101011100100111011001100001011011000010000001100010011001010111010001110111011001010110010101101110001000000110010101110110011001010111001001111001001000000110010001101001011001110110100101110100 6

#880000
0!
0,

#885000
1!
1,

#886000
b10000101 #
1$
b110 *
1.
b1100010011011000110000101101110011010110010000001101001011011100111010001100101011100100111011001100001011011000010000001101000011011110110110001100100 6

#890000
0!
0,

#895000
1!
b1000000 &
1,
b1000000 0
03

#896000
b10001000 #
0$
0.
b11010000110010101111000001000000111010001110010011101010111010001101000001000000111010001100001011000100110110001100101 6

#900000
0!
0,

#905000
1!
1,

#906000
b10001001 #
1$
1.
b110010101101110011000010110001001101100011001010010000001111010011001010111001001101111001000000110100001101111011011000110010001110011001000000110000101100011011101000110100101110110011001010010000001110011011011000110111101110100 6

#910000
0!
0,

#915000
1!
b0 &
b10001110 '
b111 (
1,
b0 0
b10001110 1
b111 2
13
b1111 4

#916000
b10001010 #
0$
0.
b1100010011011000110000101101110011010110010000001101001011011100111010001100101011100100111011001100001011011000010000001100010011001010111010001110111011001010110010101101110001000000110010101110110011001010111001001111001001000000110010001101001011001110110100101110100 6

#920000
0!
0,

#925000
1!
1,

#926000
b10001011 #
1$
b111 *
1.
b1100010011011000110000101101110011010110010000001101001011011100111010001100101011100100111011001100001011011000010000001101000011011110110110001100100 6

#930000
0!
0,

#935000
1!
b10000000 &
1,
b10000000 0
03

#936000
b10001110 #
0$
0.
b11010000110010101111000001000000111010001110010011101010111010001101000001000000111010001100001011000100110110001100101 6

#940000
0!
0,

#945000
1!
1,

#946000
b10001111 #
1$
1.
b110010101101110011000010110001001101100011001010010000001111010011001010111001001101111001000000110100001101111011011000110010001110011001000000110000101100011011101000110100101110110011001010010000001110011011011000110111101110100 6

#950000
0!
0,

#955000
1!
b0 &
b11111110 '
b0 (
1,
b0 0
b11111110 1
b0 2
13
b1000 4

#956000
b10010000 #
0$
0.
b1100010011011000110000101101110011010110010000001101001011011100111010001100101011100100111011001100001011011000010000001100010011001010111010001110111011001010110010101101110001000000110010101110110011001010111001001111001001000000110010001101001011001110110100101110100 6

#960000
0!
0,

#965000
1!
1,

#966000
b10010001 #
1$
b0 *
b1 +
1.
b1100010011011000110000101101110011010110010000001101001011011100111010001100101011100100111011001100001011011000010000001101000011011110110110001100100 6

#970000
0!
0,

#975000
1!
b1 &
1,
b1 0
03

#976000
b10010100 #
0$
0.
b11010000110010101111000001000000111010001110010011101010111010001101000001000000111010001100001011000100110110001100101 6

#980000
0!
0,

#985000
1!
1,

#986000
b10010101 #
1$
1.
b110010101101110011000010110001001101100011001010010000001111010011001010111001001101111001000000110100001101111011011000110010001110011001000000110000101100011011101000110100101110110011001010010000001110011011011000110111101110100 6

#990000
0!
0,

#995000
1!
b0 &
b11110110 '
b1 (
1,
b0 0
b11110110 1
b1 2
13
b1001 4

#996000
b10010110 #
0$
0.
b1100010011011000110000101101110011010110010000001101001011011100111010001100101011100100111011001100001011011000010000001100010011001010111010001110111011001010110010101101110001000000110010101110110011001010111001001111001001000000110010001101001011001110110100101110100 6

#1000000
0!
0,

#1005000
1!
1,

#1006000
b10010111 #
1$
b1 *
1.
b1100010011011000110000101101110011010110010000001101001011011100111010001100101011100100111011001100001011011000010000001101000011011110110110001100100 6

#1010000
0!
0,

#1015000
1!
b10 &
1,
b10 0
03

#1016000
b10011010 #
0$
0.
b11010000110010101111000001000000111010001110010011101010111010001101000001000000111010001100001011000100110110001100101 6

#1020000
0!
0,

#1025000
1!
1,

#1026000
b10011011 #
1$
1.
b110010101101110011000010110001001101100011001010010000001111010011001010111001001101111001000000110100001101111011011000110010001110011001000000110000101100011011101000110100101110110011001010010000001110011011011000110111101110100 6

#1030000
0!
0,

#1035000
1!
b0 &
b11101110 '
b10 (
1,
b0 0
b11101110 1
b10 2
13
b1010 4

#1036000
b10011100 #
0$
0.
b1100010011011000110000101101110011010110010000001101001011011100111010001100101011100100111011001100001011011000010000001100010011001010111010001110111011001010110010101101110001000000110010101110110011001010111001001111001001000000110010001101001011001110110100101110100 6

#1040000
0!
0,

#1045000
1!
1,

